{"BaseModel.932949b1-69ce-42f9-b17b-25580b23c595": {"id": "932949b1-69ce-42f9-b17b-25580b23c595", "created_at": "2021-06-28T11:58:19.339161", "updated_at": "2021-06-28T11:58:19.339168", "name": "Holberton", "my_number": 89, "__class__": "BaseModel"}, "BaseModel.458e8541-4029-4edf-bd7e-74f33f9e5ed8": {"id": "458e8541-4029-4edf-bd7e-74f33f9e5ed8", "created_at": "2021-06-28T12:23:14.696567", "updated_at": "2021-06-28T12:23:14.696572", "name": "Holberton", "my_number": 89, "__class__": "BaseModel"}, "BaseModel.399873e2-0e81-42f2-ab86-da9f0446f9d4": {"id": "399873e2-0e81-42f2-ab86-da9f0446f9d4", "created_at": "2021-06-28T12:23:38.730926", "updated_at": "2021-06-28T12:23:38.730929", "name": "Holberton", "my_number": 89, "__class__": "BaseModel"}, "BaseModel.171d37b7-a3f3-42c4-8b6a-09410050041d": {"id": "171d37b7-a3f3-42c4-8b6a-09410050041d", "created_at": "2021-06-28T12:23:41.904370", "updated_at": "2021-06-28T12:23:41.904374", "name": "Holberton", "my_number": 89, "__class__": "BaseModel"}, "BaseModel.ed8d0d02-149c-4f80-8c7e-8af375eaf00e": {"id": "ed8d0d02-149c-4f80-8c7e-8af375eaf00e", "created_at": "2021-06-28T12:24:30.883117", "updated_at": "2021-06-28T12:24:30.883120", "name": "Holberton", "my_number": 89, "__class__": "BaseModel"}}